twopct/__init__.py
twopct/base.py
Two_Percent-3.0.1.dist-info/LICENSE
Two_Percent-3.0.1.dist-info/METADATA
Two_Percent-3.0.1.dist-info/WHEEL
Two_Percent-3.0.1.dist-info/top_level.txt
Two_Percent-3.0.1.dist-info/RECORD
