Metadata-Version: 2.1
Name: Two-Percent
Version: 3.0.1
Summary: This package provides a very simple framework for making command line python scripts.
Home-page: https://bitbucket.org/notequal/two-percent/
Author: Stanley Engle
Author-email: stan.engle@gmail.com
License: BSD License
Platform: UNKNOWN
Classifier: Development Status :: 5 - Production/Stable
Classifier: Environment :: Console
Classifier: Intended Audience :: Developers
Classifier: License :: OSI Approved :: BSD License
Classifier: Natural Language :: English
Classifier: Operating System :: OS Independent
Classifier: Programming Language :: Python
Classifier: Programming Language :: Python :: 3.6
Classifier: Programming Language :: Python :: 3.7
